metadata_driver_onprem/__init__.py
metadata_driver_onprem/computing_plugin.py
metadata_driver_onprem/data_plugin.py
metadata_driver_onprem/log.py
nevermined_metadata_driver_onprem-0.2.0.dist-info/LICENSE
nevermined_metadata_driver_onprem-0.2.0.dist-info/METADATA
nevermined_metadata_driver_onprem-0.2.0.dist-info/NOTICE
nevermined_metadata_driver_onprem-0.2.0.dist-info/WHEEL
nevermined_metadata_driver_onprem-0.2.0.dist-info/top_level.txt
nevermined_metadata_driver_onprem-0.2.0.dist-info/RECORD
